CHANGELOG.md
terramare/__init__.py
terramare/classes/__init__.py
terramare/classes/from_array.py
terramare/classes/from_object.py
terramare/classes/from_value.py
terramare/classes/metadata.py
terramare/classes/utils.py
terramare/composite.py
terramare/context_factory.py
terramare/core.py
terramare/data.py
terramare/enums.py
terramare/errors.py
terramare/iterator_utils.py
terramare/mappings.py
terramare/metadata.py
terramare/newtypes.py
terramare/pretty_printer.py
terramare/primitives.py
terramare/py.typed
terramare/safe_mapping.py
terramare/sequences.py
terramare/stdlib_metadata.py
terramare/tagged_constructors.py
terramare/terramare.py
terramare/type_utils.py
terramare/types.py
terramare/unions.py
terramare-0.5.8.dist-info/LICENSE.md
terramare-0.5.8.dist-info/METADATA
terramare-0.5.8.dist-info/WHEEL
terramare-0.5.8.dist-info/RECORD
