Metadata-Version: 2.1
Name: terramare
Version: 0.5.8
Summary: Automatically construct complex objects from simple Python types.
Home-page: https://gitlab.com/tomwatson1024/terramare
License: MIT
Author: Tom W
Author-email: 796618-tomwatson1024@users.noreply.gitlab.com
Requires-Python: >=3.6.2,<4.0.0
Classifier: License :: OSI Approved :: MIT License
Classifier: Programming Language :: Python :: 3
Classifier: Programming Language :: Python :: 3.7
Classifier: Programming Language :: Python :: 3.8
Classifier: Programming Language :: Python :: 3.9
Classifier: Programming Language :: Python :: 3.10
Classifier: Programming Language :: Python :: 3.11
Classifier: Programming Language :: Python :: 3.12
Requires-Dist: dataclasses (>=0.7,<0.9) ; python_version >= "3.6" and python_version < "3.7"
Requires-Dist: python-dateutil (>=2.8.1,<3.0.0)
Requires-Dist: typing-extensions (>=3.7,<5)
Project-URL: Documentation, https://tomwatson1024.gitlab.io/terramare
Project-URL: Repository, https://gitlab.com/tomwatson1024/terramare
